vergen/Application.py
vergen/__init__.py
vergen/__main__.py
vergen/main.py
vergen-1.0.4.dist-info/METADATA
vergen-1.0.4.dist-info/WHEEL
vergen-1.0.4.dist-info/entry_points.txt
vergen-1.0.4.dist-info/top_level.txt
vergen-1.0.4.dist-info/RECORD
