Metadata-Version: 2.1
Name: vergen
Version: 1.0.4
Summary: vergen is a version generator which uses git tags to generate a branch-dependent version.
Home-page: https://gitlab.com/wxShayan/vergen
Author: Shayan Eftekhari
Author-email: shayan.eftekhari@gmail.com
Classifier: Programming Language :: Python :: 3
Classifier: Operating System :: OS Independent
Requires-Python: >=3.8
